spatialviewpy/__init__.py
spatialviewpy/__version.py
spatialviewpy/prepare_viz.py
SpatialViewPy-0.1.5.dist-info/LICENSE.txt
SpatialViewPy-0.1.5.dist-info/METADATA
SpatialViewPy-0.1.5.dist-info/WHEEL
SpatialViewPy-0.1.5.dist-info/top_level.txt
SpatialViewPy-0.1.5.dist-info/RECORD
