Metadata-Version: 2.1
Name: SpatialViewPy
Version: 0.1.5
Home-page: https://github.com/kendziorski-lab/SpatialViewPy
Author: Chitrasen Mohanty
Author-email: mohantychitraen@gmail.com
Classifier: Programming Language :: Python :: 3.6
Classifier: Operating System :: OS Independent
License-File: LICENSE.txt
Requires-Dist: requests >=2.0.0
Requires-Dist: numpy >=1.23.0
Requires-Dist: scipy >=1.10
Requires-Dist: scanpy >=1.9
Requires-Dist: anndata >=0.8
Requires-Dist: pandas >=1.5.3
Requires-Dist: zipfile2 >=0.0.12
Requires-Dist: seaborn >=0.12.2
